[
    {
        "title":"beast",
        "limbs_to_cover":[],
        "default_layers":["skin", "fat", "muscle", "bone"],
        "body":[
            {
                "title":"upper torso",
                "type":"upper torso",
                "root":"body",
                "internal":["left lung", "right lung", "heart"],
                "size":"",
                "tags":[]
            },
            {
                "title":"lower torso",
                "type":"lower torso",
                "root":"body",
                "layers":["skin", "fat", "muscle"],
                "internal":["stomach"],
                "size":"",
                "tags":[]
            },
            {
                "title":"neck",
                "type":"neck",
                "root":"upper torso",
                "layers":["skin", "fat", "muscle"],
                "internal":["neck part spine"],
                "size":"",
                "tags":[]
            },
            {
                "title":"head",
                "type":"head",
                "root":"neck",
                "internal":["brain", "tongue", "teeth"],
                "external":["left eye", "right eye", "nose", "left ear", "right ear"],
                "size":"",
                "tags":[]
            },
            {
                "title":"left front upper leg",
                "type":"upper leg",
                "root":"upper torso",
                "size":"",
                "tags":[]
            },
            {
                "title":"left front lower leg",
                "type":"lower leg",
                "root":"left front upper leg",
                "size":"",
                "tags":[]
            },
            {
                "title":"left front paw",
                "type":"paw",
                "root":"left front lower leg",
                "size":"",
                "tags":[]
            },
            {
                "title":"right front upper leg",
                "type":"upper leg",
                "root":"upper torso",
                "size":"",
                "tags":[]
            },
            {
                "title":"right front lower leg",
                "type":"lower leg",
                "root":"right front upper leg",
                "size":"",
                "tags":[]
            },
            {
                "title":"right front paw",
                "type":"paw",
                "root":"right front lower leg",
                "size":"",
                "tags":[]
            },
            {
                "title":"left rear upper leg",
                "type":"upper leg",
                "root":"lower torso",
                "size":"",
                "tags":[]
            },
            {
                "title":"left rear lower leg",
                "type":"lower leg",
                "root":"left rear upper leg",
                "size":"",
                "tags":[]
            },
            {
                "title":"left rear paw",
                "type":"paw",
                "root":"left rear lower leg",
                "size":"",
                "tags":[]
            },
            {
                "title":"right rear upper leg",
                "type":"upper leg",
                "root":"lower torso",
                "size":"",
                "tags":[]
            },
            {
                "title":"right rear lower leg",
                "type":"lower leg",
                "root":"left rear upper leg",
                "size":"",
                "tags":[]
            },
            {
                "title":"right rear paw",
                "type":"paw",
                "root":"right rear lower leg",
                "size":"",
                "tags":[]
            },
            {
                "title":"tail",
                "type":"tail",
                "root":"lower torso",
                "size":"",
                "tags":[]
            }
        ]
    },
    {
        "title":"humanoid",
        "limbs_to_cover":["foot", "upper_body", "lower_body"],
        "default_layers":["skin", "fat", "muscle", "bone"],
        "body":[
            {
                "title":"upper torso",
                "type":"upper torso",
                "root":"body",
                "internal":["left lung", "right lung", "heart"],
                "size":"",
                "tags":[]
            },
            {
                "title":"lower torso",
                "type":"lower torso",
                "root":"body",
                "layers":["skin", "fat", "muscle"],
                "internal":["stomach"],
                "size":"",
                "tags":[]
            },
            {
                "title":"neck",
                "type":"neck",
                "root":"upper torso",
                "layers":["skin", "fat", "muscle"],
                "internal":["neck part spine"],
                "size":"",
                "tags":[]
            },
            {
                "title":"head",
                "type":"head",
                "root":"neck",
                "internal":["brain", "tongue", "teeth"],
                "external":["left eye", "right eye", "nose", "left ear", "right ear"],
                "size":"",
                "tags":[]
            },
            {
                "title":"left upper arm",
                "type":"upper arm",
                "root":"upper torso",
                "size":"",
                "tags":[]
            },
            {
                "title":"left lower arm",
                "type":"lower arm",
                "root":"left upper arm",
                "size":"",
                "tags":[]
            },
            {
                "title":"left hand",
                "type":"upper arm",
                "root":"left upper arm",
                "size":"",
                "tags":["grab"]
            },
            {
                "title":"right upper arm",
                "type":"upper arm",
                "root":"upper torso",
                "size":"",
                "tags":[]
            },
            {
                "title":"right lower arm",
                "type":"lower arm",
                "root":"right upper arm",
                "size":"",
                "tags":[]
            },
            {
                "title":"right hand",
                "type":"upper arm",
                "root":"right upper arm",
                "size":"",
                "tags":["grab"]
            },
            {
                "title":"left upper leg",
                "type":"upper leg",
                "root":"lower torso",
                "size":"",
                "tags":[]
            },
            {
                "title":"left lower leg",
                "type":"lower leg",
                "root":"left upper leg",
                "size":"",
                "tags":[]
            },
            {
                "title":"left foot",
                "type":"left foot",
                "root":"left lower leg",
                "size":"",
                "tags":[]
            },
            {
                "title":"right upper leg",
                "type":"upper leg",
                "root":"lower torso",
                "size":"",
                "tags":[]
            },
            {
                "title":"right lower leg",
                "type":"lower leg",
                "root":"left upper leg",
                "size":"",
                "tags":[]
            },
            {
                "title":"right foot",
                "type":"right foot",
                "root":"right lower leg",
                "size":"",
                "tags":[]
            }
        ]
    }
]